ifrs/__init__.py
ifrs/ifrs.py
ifrs/taxonomy/__init__.py
ifrs/taxonomy/taxonomier.py
ifrs/taxonomy/ko/__init__.py
ifrs/taxonomy/ko/zip/20100430_ko.zip
ifrs/taxonomy/ko/zip/__init__.py
ifrs/taxonomy/ko/zip/ifrs20090101labko_20100203.zip
ifrs/taxonomy/ko/zip/ifrs20110325labko.zip
ifrs/taxonomy/ko/zip/taxonomy-ko-2016.zip
ifrs/taxonomy/ko/zip/trans_ko_2012.zip
ifrs/taxonomy/ko/zip/trans_ko_2013.zip
ifrs/taxonomy/ko/zip/trans_ko_2014.zip
ifrs/taxonomy/ko/zip/trans_ko_2015.zip
ifrs-0.0.0.25.dist-info/DESCRIPTION.rst
ifrs-0.0.0.25.dist-info/METADATA
ifrs-0.0.0.25.dist-info/RECORD
ifrs-0.0.0.25.dist-info/WHEEL
ifrs-0.0.0.25.dist-info/metadata.json
ifrs-0.0.0.25.dist-info/top_level.txt
