Metadata-Version: 2.0
Name: ifrs
Version: 0.0.0.25
Summary: useful tools for Korean Financial Statement disclosured on https://dart.fss.or.kr
Home-page: http://github.com/pydemia/ifrs
Author: Young-Ju Kim
Author-email: pydemia@gmail.com
License: MIT License
Platform: UNKNOWN
Classifier: Development Status :: 3 - Alpha
Classifier: Programming Language :: Python :: 3.5
Requires-Dist: python-xbrl
